{
  "sip-vs-lumpsum-investment-strategy": {
    "titleHindi": "SIP vs Lumpsum: 2026 में निवेश की सबसे अच्छी रणनीति क्या है?",
    "excerptHindi": "2026 के भारतीय बाजार में म्यूचुअल फंड निवेश के लिए SIP बेहतर है या Lumpsum? इस विस्तृत गाइड में जानें 2026 के वित्तीय आंकड़ों, ब्याज दरों और बाजार अस्थिरता के आधार पर निवेश की सर्वश्रेष्ठ रणनीति।"
  },
  "calculating-retirement-corpus-guide": {
    "titleHindi": "रिटायरमेंट कॉर्पस की गणना कैसे करें? 2026 के लिए विस्तृत गाइड",
    "excerptHindi": "2026 में भारत की बढ़ती महंगाई और स्वास्थ्य खर्चों को देखते हुए आप कैसे तय करेंगे कि आपके रिटायरमेंट के लिए कितना पैसा काफी है? जानें रिटायरमेंट कॉर्पस फंड की गणना का सही तरीका और निवेश रणनीतियां।"
  },
  "income-tax-calculator-india": {
    "titleHindi": "इनकम टैक्स गाइड 2026: नई vs पुरानी टैक्स व्यवस्था - AY 2027-28 के लिए पूरी जानकारी",
    "excerptHindi": "2026 में लागू होने वाले नए आयकर अधिनियम 2025 के अनुसार अपनी टैक्स देनदारी को समझें। जानें नई और पुरानी टैक्स व्यवस्था के स्लैब, ₹75,000 की स्टैंडर्ड डिडक्शन और टैक्स बचाने के बेहतरीन तरीके।"
  },
  "pmjjby-benefits-estimation": {
    "titleHindi": "म्यूचुअल फंड टैक्स गाइड 2026: LTCG, STCG और नए नियमों की पूरी जानकारी",
    "excerptHindi": "2026 में म्यूचुअल फंड पर टैक्स कैसे लगता है? जानें इक्विटी और डेट फंड्स के नए नियम, LTCG की ₹1.25 लाख की छूट और बजट 2026 के ताजा बदलावों के बारे में।"
  },
  "top-10-government-schemes-indian-2025-guide": {
    "titleHindi": "2026 की टॉप 10 सरकारी योजनाएं: हर भारतीय के लिए वित्तीय सुरक्षा और अवसर",
    "excerptHindi": "बजट 2026 और नया टैक्स एक्ट 2025 के बाद भारत सरकार की ये 10 योजनाएं आपके जीवन को बदल सकती हैं। जानें लखपति दीदी 2.0, पीएम विश्वकर्मा और अन्य बड़े बदलावों के बारे में।"
  },
  "top-investment-opportunities-2025-key-sectors-india": {
    "titleHindi": "2026 के टॉप निवेश अवसर: वो 7 सेक्टर्स जो आपको मालामाल बना सकते हैं",
    "excerptHindi": "2026 में निवेश कहाँ करें? जानें सेमीकंडक्टर, बायोफार्मा, AI और रिन्यूएबल ऊर्जा जैसे हाई-ग्रोथ सेक्टर्स के बारे में जो 2026-27 में बंपर रिटर्न दे सकते हैं।"
  },
  "india-new-income-tax-bill-2025-key-changes-implications": {
    "titleHindi": "New Income Tax Act 2025: भारत का नया टैक्स कानून और आपके लिए बड़े बदलाव",
    "excerptHindi": "1 अप्रैल, 2026 से लागू होने वाला"
  },
  "budget-2025-senior-citizens-top-5-expectations-financial-planning": {
    "titleHindi": "बजट 2025-26 और वरिष्ठ नागरिक: आयुष्मान भारत 70+ और नई टैक्स राहतें",
    "excerptHindi": "बजट 2025 वरिष्ठ नागरिकों के लिए खुशियों की सौगात लेकर आया है। आयुष्मान भारत योजना का 70 साल से अधिक के सभी बुजुर्गों के लिए विस्तार और FD पर 1 लाख रुपये तक की ब्याज छूट जैसे बड़े फैसले लिए गए हैं।"
  },
  "rural-ministry-mgnregs-12-percent-hike-rural-economy-impact": {
    "titleHindi": "मनरेगा (MGNREGS) की जगह अब VB-G RAM G: ग्रामीण अर्थव्यवस्था पर 12% बजट बढ़ोतरी का असर",
    "excerptHindi": "भारत सरकार ने मनरेगा की जगह"
  },
  "mgnrega-2025-new-benefits-rural-india-guide": {
    "titleHindi": "VB-G RAM G (पूर्व मनरेगा) 2025: अब 125 दिन का रोजगार और नई मजदूरी दरें",
    "excerptHindi": "नए VB-G RAM G मिशन के तहत अब ग्रामीण परिवारों को 100 की जगह 125 दिन का रोजगार मिलेगा। औसत मजदूरी भी बढ़ाकर 370 रुपये प्रतिदिन कर दी गई है। जानें आवेदन का तरीका।"
  },
  "indian-pharma-sector-2025-investment-opportunity": {
    "titleHindi": "भारतीय फार्मा क्षेत्र 2025-26: बायोफार्मा शक्ति (Biopharma SHAKTI) मिशन और निवेश के नए अवसर",
    "excerptHindi": "सरकार ने भारतीय फार्मा क्षेत्र को वैश्विक हब बनाने के लिए 10,000 करोड़ रुपये के बायोफार्मा शक्ति मिशन की घोषणा की है। बजट 2025 के बाद फार्मा शेयरों और निवेश पर क्या होगा असर?"
  },
  "effective-tax-planning-strategies-2025-maximize-savings": {
    "titleHindi": "2026 के लिए प्रभावी कर नियोजन रणनीतियाँ: नए टैक्स एक्ट 2025 में कैसे बचाएं पैसा?",
    "excerptHindi": "1 अप्रैल, 2026 से प्रभावी होने वाले"
  },
  "digital-rupee-cbdc-rbi-guide-2025": {
    "titleHindi": "Digital Rupee (CBDC) 2025-26 RBI Guide: डिजिटल रुपया क्या है और इसे कैसे इस्तेमाल करें? पूरी जानकारी",
    "excerptHindi": "भारतीय रिजर्व बैंक (RBI) ने डिजिटल रुपया (e-Rupee) 2025-26 के लिए नई गाइडलाइन्स जारी की हैं। डिजिटल रुपया और UPI में क्या अंतर है, इसके क्या फायदे हैं और आप इसे कैसे उपयोग कर सकते हैं, इस लेख में विस्तार से बताया गया है।"
  },
  "gold-monetization-scheme-2025-updates": {
    "titleHindi": "Gold Monetization Scheme (GMS) 2025-26: अपने घर के सोने पर पाएं ब्याज! एक विस्तृत गाइड",
    "excerptHindi": "क्या आप जानते हैं कि आपके घर में रखा सोना आपके लिए नियमित आय का जरिया बन सकता है? गोल्ड मोनेटाइजेशन स्कीम (GMS) 2025-26 के नए नियमों, ब्याज दरों और इसके फायदों के बारे में यहाँ विस्तार से जानें।"
  },
  "mutual-fund-taxation-rules-2025": {
    "titleHindi": "Mutual Fund Taxation 2025-26: म्यूचुअल फंड पर टैक्स के नए नियम! क्या बदल गया?",
    "excerptHindi": "म्यूचुअल फंड निवेश पर 2025-26 में टैक्स के क्या नियम हैं? LTCG, STCG और SIP पर लगने वाले टैक्स की पूरी गणना यहाँ समझें। बजट 2024-25 के बाद हुए बदलावों का विश्लेषण।"
  },
  "health-insurance-gst-exemption-2025": {
    "titleHindi": "Health Insurance GST Exemption 2025-26: स्वास्थ्य बीमा पर GST में बड़ी राहत! अब प्रीमियम होगा कम",
    "excerptHindi": "2025-26 में स्वास्थ्य बीमा (Health Insurance) पर GST नियमों में बड़े बदलाव हुए हैं। वरिष्ठ नागरिकों के लिए पूरी छूट और अन्य के लिए कम दरों का आपकी जेब पर क्या असर होगा? यहाँ पूरी जानकारी विस्तार से जानें।"
  },
  "startup-india-seed-fund-2025": {
    "titleHindi": "Start-up India Seed Fund Scheme (SISFS) 2025-24: नए स्टार्टअप्स के लिए ₹50 लाख तक की फंडिंग! पूरी जानकारी",
    "excerptHindi": "क्या आप अपना नया बिजनेस शुरू करना चाहते हैं? स्टार्टअप इंडिया सीड फंड स्कीम (SISFS) 2025-26 के तहत सरकार दे रही है ₹50 लाख तक की मदद। पात्रता, आवेदन और फायदों की पूरी जानकारी यहाँ पढ़ें।"
  },
  "rera-real-estate-guide-2025": {
    "titleHindi": "RERA 2025-26: घर खरीदने से पहले जानें ये नियम! रेरा (RERA) गाइड और आपके अधिकार",
    "excerptHindi": "क्या आप अपना सपनों का घर खरीदने की सोच रहे हैं? RERA 2025-26 के नए नियमों, बिल्डरों की जिम्मेदारियों और घर खरीदारों के अधिकारों को इस विस्तृत गाइड में समझें। धोखाधड़ी से बचने के आसान तरीके।"
  },
  "sip-fd-se-aage-nivesh-vichar-2025": {
    "titleHindi": "SIP और FD से आगे: 2025 में लोकप्रियता हासिल कर रहे 5 नए निवेश विचार",
    "excerptHindi": "क्या आप केवल SIP और FD में निवेश कर रहे हैं? 2025 में निवेश के नए रास्ते खुल रहे हैं! जानें AI ETFs, Crypto SIP, और Green Bonds जैसे 5 उभरते निवेश विचार जो आपको बेहतर रिटर्न दिला सकते हैं।"
  },
  "gold-investment-guide-2025-physical-etf-sgb": {
    "titleHindi": "Gold Investment 2025: फिजिकल गोल्ड, ETF या SGB? आपके निवेश के लिए क्या है बेहतर?",
    "excerptHindi": "2025 में सोने की कीमतें रिकॉर्ड तोड़ रही हैं। क्या आपको अभी सोना खरीदना चाहिए? जानें फिजिकल गोल्ड, गोल्ड ईटीएफ और सॉवरेन गोल्ड बॉन्ड (SGB) के बीच का अंतर और आपके लिए सबसे अच्छा विकल्प क्या है।"
  }
}